django_excel_tools/__init__.py
django_excel_tools/exceptions.py
django_excel_tools/fields.py
django_excel_tools/serializers.py
django_excel_tools/utils.py
django_excel_tools/locale/ja/LC_MESSAGES/django.mo
django_excel_tools/locale/km/LC_MESSAGES/django.mo
django_excel_tools/locale/th/LC_MESSAGES/django.mo
django_excel_tools-1.1.1.dist-info/AUTHORS.rst
django_excel_tools-1.1.1.dist-info/LICENSE
django_excel_tools-1.1.1.dist-info/METADATA
django_excel_tools-1.1.1.dist-info/WHEEL
django_excel_tools-1.1.1.dist-info/top_level.txt
django_excel_tools-1.1.1.dist-info/RECORD
