Metadata-Version: 2.1
Name: django_excel_tools
Version: 1.1.1
Summary: Common function when working with excel.
Home-page: https://github.com/NorakGithub/django-excel-tools
Author: Khemanorak Khath
Author-email: khath.khemanorak@gmail.com
License: MIT license
Keywords: django,excel,tools
Classifier: Development Status :: 2 - Pre-Alpha
Classifier: Intended Audience :: Developers
Classifier: License :: OSI Approved :: MIT License
Classifier: Natural Language :: English
Classifier: Programming Language :: Python :: 2
Classifier: Programming Language :: Python :: 2.6
Classifier: Programming Language :: Python :: 2.7
Classifier: Programming Language :: Python :: 3
Classifier: Programming Language :: Python :: 3.3
Classifier: Programming Language :: Python :: 3.4
Classifier: Programming Language :: Python :: 3.5
License-File: LICENSE
License-File: AUTHORS.rst
